src/decoder.v
module decoder_8_to_256 (
    input  [7:0] in,
    input        enable, 
    output [255:0] out
);
    // If enable is high, shift a single '1' to the position indicated by the input.
    // If enable is low, output all zeros.
    // This single line generates a massive, perfect 256-output logic tree in hardware.
    assign out = enable ? (256'b1 << in) : 256'b0;

endmodule

src/decodertb.v
`timescale 1ns / 1ps

module tb_decoder();

    // Inputs
    reg [7:0] in;
    reg enable;

    // Outputs
    wire [255:0] out;

    // Instantiate the Unit Under Test (UUT)
    decoder_8_to_256 uut (
        .in(in), 
        .enable(enable),
        .out(out)
    );

    integer i;

    // VCD Dumping Block
    initial begin
        $dumpfile("decoder_waveform.vcd"); 
        $dumpvars(0, tb_decoder);          
    end

    // Automated Verification Block
    initial begin
        $display("-------------------------------------------");
        $display("Starting 8-to-256 Decoder Verification...");
        
        // Test 1: Check Enable Low behavior
        enable = 1'b0;
        in = 8'd15; // Random input
        #10;
        if (out !== 256'b0) begin
            $display("FAIL: Decoder output is not zero when disabled!");
        end

        // Test 2: Check all 256 combinations when Enabled
        enable = 1'b1;
        for (i = 0; i < 256; i = i + 1) begin
            in = i;
            #10;
            
            // The expected result is a 1 shifted left by 'i' positions
            if (out !== (256'b1 << i)) begin
                $display("FAIL: Decoder logic incorrect at input %d", i);
            end
        end

        $display("Simulation Complete. All 256 states verified successfully.");
        $display("-------------------------------------------");
        $finish; 
    end
endmodule

src/decoder_waveform.vcd
$date
	Thu Jun 25 20:50:13 2026
$end
$version
	Icarus Verilog
$end
$timescale
	1ps
$end
$scope module tb_decoder $end
$var wire 256 ! out [255:0] $end
$var reg 1 " enable $end
$var reg 8 # in [7:0] $end
$var integer 32 $ i [31:0] $end
$scope module uut $end
$var wire 1 " enable $end
$var wire 8 % in [7:0] $end
$var wire 256 & out [255:0] $end
$upscope $end
$upscope $end
$enddefinitions $end
$comment Show the parameter values. $end
$dumpall
$end
#0
$dumpvars
b0 &
b1111 %
bx $
b1111 #
0"
b0 !
$end
#10000
b1 !
b1 &
b0 #
b0 %
b0 $
1"
#20000
b10 !
b10 &
b1 #
b1 %
b1 $
#30000
b100 !
b100 &
b10 #
b10 %
b10 $
#40000
b1000 !
b1000 &
b11 #
b11 %
b11 $
#50000
b10000 !
b10000 &
b100 #
b100 %
b100 $
#60000
b100000 !
b100000 &
b101 #
b101 %
b101 $
#70000
b1000000 !
b1000000 &
b110 #
b110 %
b110 $
#80000
b10000000 !
b10000000 &
b111 #
b111 %
b111 $
#90000
b100000000 !
b100000000 &
b1000 #
b1000 %
b1000 $
#100000
b1000000000 !
b1000000000 &
b1001 #
b1001 %
b1001 $
#110000
b10000000000 !
b10000000000 &
b1010 #
b1010 %
b1010 $
#120000
b100000000000 !
b100000000000 &
b1011 #
b1011 %
b1011 $
#130000
b1000000000000 !
b1000000000000 &
b1100 #
b1100 %
b1100 $
#140000
b10000000000000 !
b10000000000000 &
b1101 #
b1101 %
b1101 $
#150000
b100000000000000 !
b100000000000000 &
b1110 #
b1110 %
b1110 $
#160000
b1000000000000000 !
b1000000000000000 &
b1111 #
b1111 %
b1111 $
#170000
b10000000000000000 !
b10000000000000000 &
b10000 #
b10000 %
b10000 $
#180000
b100000000000000000 !
b100000000000000000 &
b10001 #
b10001 %
b10001 $
#190000
b1000000000000000000 !
b1000000000000000000 &
b10010 #
b10010 %
b10010 $
#200000
b10000000000000000000 !
b10000000000000000000 &
b10011 #
b10011 %
b10011 $
#210000
b100000000000000000000 !
b100000000000000000000 &
b10100 #
b10100 %
b10100 $
#220000
b1000000000000000000000 !
b1000000000000000000000 &
b10101 #
b10101 %
b10101 $
#230000
b10000000000000000000000 !
b10000000000000000000000 &
b10110 #
b10110 %
b10110 $
#240000
b100000000000000000000000 !
b100000000000000000000000 &
b10111 #
b10111 %
b10111 $
#250000
b1000000000000000000000000 !
b1000000000000000000000000 &
b11000 #
b11000 %
b11000 $
#260000
b10000000000000000000000000 !
b10000000000000000000000000 &
b11001 #
b11001 %
b11001 $
#270000
b100000000000000000000000000 !
b100000000000000000000000000 &
b11010 #
b11010 %
b11010 $
#280000
b1000000000000000000000000000 !
b1000000000000000000000000000 &
b11011 #
b11011 %
b11011 $
#290000
b10000000000000000000000000000 !
b10000000000000000000000000000 &
b11100 #
b11100 %
b11100 $
#300000
b100000000000000000000000000000 !
b100000000000000000000000000000 &
b11101 #
b11101 %
b11101 $
#310000
b1000000000000000000000000000000 !
b1000000000000000000000000000000 &
b11110 #
b11110 %
b11110 $
#320000
b10000000000000000000000000000000 !
b10000000000000000000000000000000 &
b11111 #
b11111 %
b11111 $
#330000
b100000000000000000000000000000000 !
b100000000000000000000000000000000 &
b100000 #
b100000 %
b100000 $
#340000
b1000000000000000000000000000000000 !
b1000000000000000000000000000000000 &
b100001 #
b100001 %
b100001 $
#350000
b10000000000000000000000000000000000 !
b10000000000000000000000000000000000 &
b100010 #
b100010 %
b100010 $
#360000
b100000000000000000000000000000000000 !
b100000000000000000000000000000000000 &
b100011 #
b100011 %
b100011 $
#370000
b1000000000000000000000000000000000000 !
b1000000000000000000000000000000000000 &
b100100 #
b100100 %
b100100 $
#380000
b10000000000000000000000000000000000000 !
b10000000000000000000000000000000000000 &
b100101 #
b100101 %
b100101 $
#390000
b100000000000000000000000000000000000000 !
b100000000000000000000000000000000000000 &
b100110 #
b100110 %
b100110 $
#400000
b1000000000000000000000000000000000000000 !
b1000000000000000000000000000000000000000 &
b100111 #
b100111 %
b100111 $
#410000
b10000000000000000000000000000000000000000 !
b10000000000000000000000000000000000000000 &
b101000 #
b101000 %
b101000 $
#420000
b100000000000000000000000000000000000000000 !
b100000000000000000000000000000000000000000 &
b101001 #
b101001 %
b101001 $
#430000
b1000000000000000000000000000000000000000000 !
b1000000000000000000000000000000000000000000 &
b101010 #
b101010 %
b101010 $
#440000
b10000000000000000000000000000000000000000000 !
b10000000000000000000000000000000000000000000 &
b101011 #
b101011 %
b101011 $
#450000
b100000000000000000000000000000000000000000000 !
b100000000000000000000000000000000000000000000 &
b101100 #
b101100 %
b101100 $
#460000
b1000000000000000000000000000000000000000000000 !
b1000000000000000000000000000000000000000000000 &
b101101 #
b101101 %
b101101 $
#470000
b10000000000000000000000000000000000000000000000 !
b10000000000000000000000000000000000000000000000 &
b101110 #
b101110 %
b101110 $
#480000
b100000000000000000000000000000000000000000000000 !
b100000000000000000000000000000000000000000000000 &
b101111 #
b101111 %
b101111 $
#490000
b1000000000000000000000000000000000000000000000000 !
b1000000000000000000000000000000000000000000000000 &
b110000 #
b110000 %
b110000 $
#500000
b10000000000000000000000000000000000000000000000000 !
b10000000000000000000000000000000000000000000000000 &
b110001 #
b110001 %
b110001 $
#510000
b100000000000000000000000000000000000000000000000000 !
b100000000000000000000000000000000000000000000000000 &
b110010 #
b110010 %
b110010 $
#520000
b1000000000000000000000000000000000000000000000000000 !
b1000000000000000000000000000000000000000000000000000 &
b110011 #
b110011 %
b110011 $
#530000
b10000000000000000000000000000000000000000000000000000 !
b10000000000000000000000000000000000000000000000000000 &
b110100 #
b110100 %
b110100 $
#540000
b100000000000000000000000000000000000000000000000000000 !
b100000000000000000000000000000000000000000000000000000 &
b110101 #
b110101 %
b110101 $
#550000
b1000000000000000000000000000000000000000000000000000000 !
b1000000000000000000000000000000000000000000000000000000 &
b110110 #
b110110 %
b110110 $
#560000
b10000000000000000000000000000000000000000000000000000000 !
b10000000000000000000000000000000000000000000000000000000 &
b110111 #
b110111 %
b110111 $
#570000
b100000000000000000000000000000000000000000000000000000000 !
b100000000000000000000000000000000000000000000000000000000 &
b111000 #
b111000 %
b111000 $
#580000
b1000000000000000000000000000000000000000000000000000000000 !
b1000000000000000000000000000000000000000000000000000000000 &
b111001 #
b111001 %
b111001 $
#590000
b10000000000000000000000000000000000000000000000000000000000 !
b10000000000000000000000000000000000000000000000000000000000 &
b111010 #
b111010 %
b111010 $
#600000
b100000000000000000000000000000000000000000000000000000000000 !
b100000000000000000000000000000000000000000000000000000000000 &
b111011 #
b111011 %
b111011 $
#610000
b1000000000000000000000000000000000000000000000000000000000000 !
b1000000000000000000000000000000000000000000000000000000000000 &
b111100 #
b111100 %
b111100 $
#620000
b10000000000000000000000000000000000000000000000000000000000000 !
b10000000000000000000000000000000000000000000000000000000000000 &
b111101 #
b111101 %
b111101 $
#630000
b100000000000000000000000000000000000000000000000000000000000000 !
b100000000000000000000000000000000000000000000000000000000000000 &
b111110 #
b111110 %
b111110 $
#640000
b1000000000000000000000000000000000000000000000000000000000000000 !
b1000000000000000000000000000000000000000000000000000000000000000 &
b111111 #
b111111 %
b111111 $
#650000
b10000000000000000000000000000000000000000000000000000000000000000 !
b10000000000000000000000000000000000000000000000000000000000000000 &
b1000000 #
b1000000 %
b1000000 $
#660000
b100000000000000000000000000000000000000000000000000000000000000000 !
b100000000000000000000000000000000000000000000000000000000000000000 &
b1000001 #
b1000001 %
b1000001 $
#670000
b1000000000000000000000000000000000000000000000000000000000000000000 !
b1000000000000000000000000000000000000000000000000000000000000000000 &
b1000010 #
b1000010 %
b1000010 $
#680000
b10000000000000000000000000000000000000000000000000000000000000000000 !
b10000000000000000000000000000000000000000000000000000000000000000000 &
b1000011 #
b1000011 %
b1000011 $
#690000
b100000000000000000000000000000000000000000000000000000000000000000000 !
b100000000000000000000000000000000000000000000000000000000000000000000 &
b1000100 #
b1000100 %
b1000100 $
#700000
b1000000000000000000000000000000000000000000000000000000000000000000000 !
b1000000000000000000000000000000000000000000000000000000000000000000000 &
b1000101 #
b1000101 %
b1000101 $
#710000
b10000000000000000000000000000000000000000000000000000000000000000000000 !
b10000000000000000000000000000000000000000000000000000000000000000000000 &
b1000110 #
b1000110 %
b1000110 $
#720000
b100000000000000000000000000000000000000000000000000000000000000000000000 !
b100000000000000000000000000000000000000000000000000000000000000000000000 &
b1000111 #
b1000111 %
b1000111 $
#730000
b1000000000000000000000000000000000000000000000000000000000000000000000000 !
b1000000000000000000000000000000000000000000000000000000000000000000000000 &
b1001000 #
b1001000 %
b1001000 $
#740000
b10000000000000000000000000000000000000000000000000000000000000000000000000 !
b10000000000000000000000000000000000000000000000000000000000000000000000000 &
b1001001 #
b1001001 %
b1001001 $
#750000
b100000000000000000000000000000000000000000000000000000000000000000000000000 !
b100000000000000000000000000000000000000000000000000000000000000000000000000 &
b1001010 #
b1001010 %
b1001010 $
#760000
b1000000000000000000000000000000000000000000000000000000000000000000000000000 !
b1000000000000000000000000000000000000000000000000000000000000000000000000000 &
b1001011 #
b1001011 %
b1001011 $
#770000
b10000000000000000000000000000000000000000000000000000000000000000000000000000 !
b10000000000000000000000000000000000000000000000000000000000000000000000000000 &
b1001100 #
b1001100 %
b1001100 $
#780000
b100000000000000000000000000000000000000000000000000000000000000000000000000000 !
b100000000000000000000000000000000000000000000000000000000000000000000000000000 &
b1001101 #
b1001101 %
b1001101 $
#790000
b1000000000000000000000000000000000000000000000000000000000000000000000000000000 !
b1000000000000000000000000000000000000000000000000000000000000000000000000000000 &
b1001110 #
b1001110 %
b1001110 $
#800000
b10000000000000000000000000000000000000000000000000000000000000000000000000000000 !
b10000000000000000000000000000000000000000000000000000000000000000000000000000000 &
b1001111 #
b1001111 %
b1001111 $
#810000
b100000000000000000000000000000000000000000000000000000000000000000000000000000000 !
b100000000000000000000000000000000000000000000000000000000000000000000000000000000 &
b1010000 #
b1010000 %
b1010000 $
#820000
b1000000000000000000000000000000000000000000000000000000000000000000000000000000000 !
b1000000000000000000000000000000000000000000000000000000000000000000000000000000000 &
b1010001 #
b1010001 %
b1010001 $
#830000
b10000000000000000000000000000000000000000000000000000000000000000000000000000000000 !
b10000000000000000000000000000000000000000000000000000000000000000000000000000000000 &
b1010010 #
b1010010 %
b1010010 $
#840000
b100000000000000000000000000000000000000000000000000000000000000000000000000000000000 !
b100000000000000000000000000000000000000000000000000000000000000000000000000000000000 &
b1010011 #
b1010011 %
b1010011 $
#850000
b1000000000000000000000000000000000000000000000000000000000000000000000000000000000000 !
b1000000000000000000000000000000000000000000000000000000000000000000000000000000000000 &
b1010100 #
b1010100 %
b1010100 $
#860000
b10000000000000000000000000000000000000000000000000000000000000000000000000000000000000 !
b10000000000000000000000000000000000000000000000000000000000000000000000000000000000000 &
b1010101 #
b1010101 %
b1010101 $
#870000
b100000000000000000000000000000000000000000000000000000000000000000000000000000000000000 !
b100000000000000000000000000000000000000000000000000000000000000000000000000000000000000 &
b1010110 #
b1010110 %
b1010110 $
#880000
b1000000000000000000000000000000000000000000000000000000000000000000000000000000000000000 !
b1000000000000000000000000000000000000000000000000000000000000000000000000000000000000000 &
b1010111 #
b1010111 %
b1010111 $
#890000
b10000000000000000000000000000000000000000000000000000000000000000000000000000000000000000 !
b10000000000000000000000000000000000000000000000000000000000000000000000000000000000000000 &
b1011000 #
b1011000 %
b1011000 $
#900000
b100000000000000000000000000000000000000000000000000000000000000000000000000000000000000000 !
b100000000000000000000000000000000000000000000000000000000000000000000000000000000000000000 &
b1011001 #
b1011001 %
b1011001 $
#910000
b1000000000000000000000000000000000000000000000000000000000000000000000000000000000000000000 !
b1000000000000000000000000000000000000000000000000000000000000000000000000000000000000000000 &
b1011010 #
b1011010 %
b1011010 $
#920000
b10000000000000000000000000000000000000000000000000000000000000000000000000000000000000000000 !
b10000000000000000000000000000000000000000000000000000000000000000000000000000000000000000000 &
b1011011 #
b1011011 %
b1011011 $
#930000
b100000000000000000000000000000000000000000000000000000000000000000000000000000000000000000000 !
b100000000000000000000000000000000000000000000000000000000000000000000000000000000000000000000 &
b1011100 #
b1011100 %
b1011100 $
#940000
b1000000000000000000000000000000000000000000000000000000000000000000000000000000000000000000000 !
b1000000000000000000000000000000000000000000000000000000000000000000000000000000000000000000000 &
b1011101 #
b1011101 %
b1011101 $
#950000
b10000000000000000000000000000000000000000000000000000000000000000000000000000000000000000000000 !
b10000000000000000000000000000000000000000000000000000000000000000000000000000000000000000000000 &
b1011110 #
b1011110 %
b1011110 $
#960000
b100000000000000000000000000000000000000000000000000000000000000000000000000000000000000000000000 !
b100000000000000000000000000000000000000000000000000000000000000000000000000000000000000000000000 &
b1011111 #
b1011111 %
b1011111 $
#970000
b1000000000000000000000000000000000000000000000000000000000000000000000000000000000000000000000000 !
b1000000000000000000000000000000000000000000000000000000000000000000000000000000000000000000000000 &
b1100000 #
b1100000 %
b1100000 $
#980000
b10000000000000000000000000000000000000000000000000000000000000000000000000000000000000000000000000 !
b10000000000000000000000000000000000000000000000000000000000000000000000000000000000000000000000000 &
b1100001 #
b1100001 %
b1100001 $
#990000
b100000000000000000000000000000000000000000000000000000000000000000000000000000000000000000000000000 !
b100000000000000000000000000000000000000000000000000000000000000000000000000000000000000000000000000 &
b1100010 #
b1100010 %
b1100010 $
#1000000
b1000000000000000000000000000000000000000000000000000000000000000000000000000000000000000000000000000 !
b1000000000000000000000000000000000000000000000000000000000000000000000000000000000000000000000000000 &
b1100011 #
b1100011 %
b1100011 $
#1010000
b10000000000000000000000000000000000000000000000000000000000000000000000000000000000000000000000000000 !
b10000000000000000000000000000000000000000000000000000000000000000000000000000000000000000000000000000 &
b1100100 #
b1100100 %
b1100100 $
#1020000
b100000000000000000000000000000000000000000000000000000000000000000000000000000000000000000000000000000 !
b100000000000000000000000000000000000000000000000000000000000000000000000000000000000000000000000000000 &
b1100101 #
b1100101 %
b1100101 $
#1030000
b1000000000000000000000000000000000000000000000000000000000000000000000000000000000000000000000000000000 !
b1000000000000000000000000000000000000000000000000000000000000000000000000000000000000000000000000000000 &
b1100110 #
b1100110 %
b1100110 $
#1040000
b10000000000000000000000000000000000000000000000000000000000000000000000000000000000000000000000000000000 !
b10000000000000000000000000000000000000000000000000000000000000000000000000000000000000000000000000000000 &
b1100111 #
b1100111 %
b1100111 $
#1050000
b100000000000000000000000000000000000000000000000000000000000000000000000000000000000000000000000000000000 !
b100000000000000000000000000000000000000000000000000000000000000000000000000000000000000000000000000000000 &
b1101000 #
b1101000 %
b1101000 $
#1060000
b1000000000000000000000000000000000000000000000000000000000000000000000000000000000000000000000000000000000 !
b1000000000000000000000000000000000000000000000000000000000000000000000000000000000000000000000000000000000 &
b1101001 #
b1101001 %
b1101001 $
#1070000
b10000000000000000000000000000000000000000000000000000000000000000000000000000000000000000000000000000000000 !
b10000000000000000000000000000000000000000000000000000000000000000000000000000000000000000000000000000000000 &
b1101010 #
b1101010 %
b1101010 $
#1080000
b100000000000000000000000000000000000000000000000000000000000000000000000000000000000000000000000000000000000 !
b100000000000000000000000000000000000000000000000000000000000000000000000000000000000000000000000000000000000 &
b1101011 #
b1101011 %
b1101011 $
#1090000
b1000000000000000000000000000000000000000000000000000000000000000000000000000000000000000000000000000000000000 !
b1000000000000000000000000000000000000000000000000000000000000000000000000000000000000000000000000000000000000 &
b1101100 #
b1101100 %
b1101100 $
#1100000
b10000000000000000000000000000000000000000000000000000000000000000000000000000000000000000000000000000000000000 !
b10000000000000000000000000000000000000000000000000000000000000000000000000000000000000000000000000000000000000 &
b1101101 #
b1101101 %
b1101101 $
#1110000
b100000000000000000000000000000000000000000000000000000000000000000000000000000000000000000000000000000000000000 !
b100000000000000000000000000000000000000000000000000000000000000000000000000000000000000000000000000000000000000 &
b1101110 #
b1101110 %
b1101110 $
#1120000
b1000000000000000000000000000000000000000000000000000000000000000000000000000000000000000000000000000000000000000 !
b1000000000000000000000000000000000000000000000000000000000000000000000000000000000000000000000000000000000000000 &
b1101111 #
b1101111 %
b1101111 $
#1130000
b10000000000000000000000000000000000000000000000000000000000000000000000000000000000000000000000000000000000000000 !
b10000000000000000000000000000000000000000000000000000000000000000000000000000000000000000000000000000000000000000 &
b1110000 #
b1110000 %
b1110000 $
#1140000
b100000000000000000000000000000000000000000000000000000000000000000000000000000000000000000000000000000000000000000 !
b100000000000000000000000000000000000000000000000000000000000000000000000000000000000000000000000000000000000000000 &
b1110001 #
b1110001 %
b1110001 $
#1150000
b1000000000000000000000000000000000000000000000000000000000000000000000000000000000000000000000000000000000000000000 !
b1000000000000000000000000000000000000000000000000000000000000000000000000000000000000000000000000000000000000000000 &
b1110010 #
b1110010 %
b1110010 $
#1160000
b10000000000000000000000000000000000000000000000000000000000000000000000000000000000000000000000000000000000000000000 !
b10000000000000000000000000000000000000000000000000000000000000000000000000000000000000000000000000000000000000000000 &
b1110011 #
b1110011 %
b1110011 $
#1170000
b100000000000000000000000000000000000000000000000000000000000000000000000000000000000000000000000000000000000000000000 !
b100000000000000000000000000000000000000000000000000000000000000000000000000000000000000000000000000000000000000000000 &
b1110100 #
b1110100 %
b1110100 $
#1180000
b1000000000000000000000000000000000000000000000000000000000000000000000000000000000000000000000000000000000000000000000 !
b1000000000000000000000000000000000000000000000000000000000000000000000000000000000000000000000000000000000000000000000 &
b1110101 #
b1110101 %
b1110101 $
#1190000
b10000000000000000000000000000000000000000000000000000000000000000000000000000000000000000000000000000000000000000000000 !
b10000000000000000000000000000000000000000000000000000000000000000000000000000000000000000000000000000000000000000000000 &
b1110110 #
b1110110 %
b1110110 $
#1200000
b100000000000000000000000000000000000000000000000000000000000000000000000000000000000000000000000000000000000000000000000 !
b100000000000000000000000000000000000000000000000000000000000000000000000000000000000000000000000000000000000000000000000 &
b1110111 #
b1110111 %
b1110111 $
#1210000
b1000000000000000000000000000000000000000000000000000000000000000000000000000000000000000000000000000000000000000000000000 !
b1000000000000000000000000000000000000000000000000000000000000000000000000000000000000000000000000000000000000000000000000 &
b1111000 #
b1111000 %
b1111000 $
#1220000
b10000000000000000000000000000000000000000000000000000000000000000000000000000000000000000000000000000000000000000000000000 !
b10000000000000000000000000000000000000000000000000000000000000000000000000000000000000000000000000000000000000000000000000 &
b1111001 #
b1111001 %
b1111001 $
#1230000
b100000000000000000000000000000000000000000000000000000000000000000000000000000000000000000000000000000000000000000000000000 !
b100000000000000000000000000000000000000000000000000000000000000000000000000000000000000000000000000000000000000000000000000 &
b1111010 #
b1111010 %
b1111010 $
#1240000
b1000000000000000000000000000000000000000000000000000000000000000000000000000000000000000000000000000000000000000000000000000 !
b1000000000000000000000000000000000000000000000000000000000000000000000000000000000000000000000000000000000000000000000000000 &
b1111011 #
b1111011 %
b1111011 $
#1250000
b10000000000000000000000000000000000000000000000000000000000000000000000000000000000000000000000000000000000000000000000000000 !
b10000000000000000000000000000000000000000000000000000000000000000000000000000000000000000000000000000000000000000000000000000 &
b1111100 #
b1111100 %
b1111100 $
#1260000
b100000000000000000000000000000000000000000000000000000000000000000000000000000000000000000000000000000000000000000000000000000 !
b100000000000000000000000000000000000000000000000000000000000000000000000000000000000000000000000000000000000000000000000000000 &
b1111101 #
b1111101 %
b1111101 $
#1270000
b1000000000000000000000000000000000000000000000000000000000000000000000000000000000000000000000000000000000000000000000000000000 !
b1000000000000000000000000000000000000000000000000000000000000000000000000000000000000000000000000000000000000000000000000000000 &
b1111110 #
b1111110 %
b1111110 $
#1280000
b10000000000000000000000000000000000000000000000000000000000000000000000000000000000000000000000000000000000000000000000000000000 !
b10000000000000000000000000000000000000000000000000000000000000000000000000000000000000000000000000000000000000000000000000000000 &
b1111111 #
b1111111 %
b1111111 $
#1290000
b100000000000000000000000000000000000000000000000000000000000000000000000000000000000000000000000000000000000000000000000000000000 !
b100000000000000000000000000000000000000000000000000000000000000000000000000000000000000000000000000000000000000000000000000000000 &
b10000000 #
b10000000 %
b10000000 $
#1300000
b1000000000000000000000000000000000000000000000000000000000000000000000000000000000000000000000000000000000000000000000000000000000 !
b1000000000000000000000000000000000000000000000000000000000000000000000000000000000000000000000000000000000000000000000000000000000 &
b10000001 #
b10000001 %
b10000001 $
#1310000
b10000000000000000000000000000000000000000000000000000000000000000000000000000000000000000000000000000000000000000000000000000000000 !
b10000000000000000000000000000000000000000000000000000000000000000000000000000000000000000000000000000000000000000000000000000000000 &
b10000010 #
b10000010 %
b10000010 $
#1320000
b100000000000000000000000000000000000000000000000000000000000000000000000000000000000000000000000000000000000000000000000000000000000 !
b100000000000000000000000000000000000000000000000000000000000000000000000000000000000000000000000000000000000000000000000000000000000 &
b10000011 #
b10000011 %
b10000011 $
#1330000
b1000000000000000000000000000000000000000000000000000000000000000000000000000000000000000000000000000000000000000000000000000000000000 !
b1000000000000000000000000000000000000000000000000000000000000000000000000000000000000000000000000000000000000000000000000000000000000 &
b10000100 #
b10000100 %
b10000100 $
#1340000
b10000000000000000000000000000000000000000000000000000000000000000000000000000000000000000000000000000000000000000000000000000000000000 !
b10000000000000000000000000000000000000000000000000000000000000000000000000000000000000000000000000000000000000000000000000000000000000 &
b10000101 #
b10000101 %
b10000101 $
#1350000
b100000000000000000000000000000000000000000000000000000000000000000000000000000000000000000000000000000000000000000000000000000000000000 !
b100000000000000000000000000000000000000000000000000000000000000000000000000000000000000000000000000000000000000000000000000000000000000 &
b10000110 #
b10000110 %
b10000110 $
#1360000
b1000000000000000000000000000000000000000000000000000000000000000000000000000000000000000000000000000000000000000000000000000000000000000 !
b1000000000000000000000000000000000000000000000000000000000000000000000000000000000000000000000000000000000000000000000000000000000000000 &
b10000111 #
b10000111 %
b10000111 $
#1370000
b10000000000000000000000000000000000000000000000000000000000000000000000000000000000000000000000000000000000000000000000000000000000000000 !
b10000000000000000000000000000000000000000000000000000000000000000000000000000000000000000000000000000000000000000000000000000000000000000 &
b10001000 #
b10001000 %
b10001000 $
#1380000
b100000000000000000000000000000000000000000000000000000000000000000000000000000000000000000000000000000000000000000000000000000000000000000 !
b100000000000000000000000000000000000000000000000000000000000000000000000000000000000000000000000000000000000000000000000000000000000000000 &
b10001001 #
b10001001 %
b10001001 $
#1390000
b1000000000000000000000000000000000000000000000000000000000000000000000000000000000000000000000000000000000000000000000000000000000000000000 !
b1000000000000000000000000000000000000000000000000000000000000000000000000000000000000000000000000000000000000000000000000000000000000000000 &
b10001010 #
b10001010 %
b10001010 $
#1400000
b10000000000000000000000000000000000000000000000000000000000000000000000000000000000000000000000000000000000000000000000000000000000000000000 !
b10000000000000000000000000000000000000000000000000000000000000000000000000000000000000000000000000000000000000000000000000000000000000000000 &
b10001011 #
b10001011 %
b10001011 $
#1410000
b100000000000000000000000000000000000000000000000000000000000000000000000000000000000000000000000000000000000000000000000000000000000000000000 !
b100000000000000000000000000000000000000000000000000000000000000000000000000000000000000000000000000000000000000000000000000000000000000000000 &
b10001100 #
b10001100 %
b10001100 $
#1420000
b1000000000000000000000000000000000000000000000000000000000000000000000000000000000000000000000000000000000000000000000000000000000000000000000 !
b1000000000000000000000000000000000000000000000000000000000000000000000000000000000000000000000000000000000000000000000000000000000000000000000 &
b10001101 #
b10001101 %
b10001101 $
#1430000
b10000000000000000000000000000000000000000000000000000000000000000000000000000000000000000000000000000000000000000000000000000000000000000000000 !
b10000000000000000000000000000000000000000000000000000000000000000000000000000000000000000000000000000000000000000000000000000000000000000000000 &
b10001110 #
b10001110 %
b10001110 $
#1440000
b100000000000000000000000000000000000000000000000000000000000000000000000000000000000000000000000000000000000000000000000000000000000000000000000 !
b100000000000000000000000000000000000000000000000000000000000000000000000000000000000000000000000000000000000000000000000000000000000000000000000 &
b10001111 #
b10001111 %
b10001111 $
#1450000
b1000000000000000000000000000000000000000000000000000000000000000000000000000000000000000000000000000000000000000000000000000000000000000000000000 !
b1000000000000000000000000000000000000000000000000000000000000000000000000000000000000000000000000000000000000000000000000000000000000000000000000 &
b10010000 #
b10010000 %
b10010000 $
#1460000
b10000000000000000000000000000000000000000000000000000000000000000000000000000000000000000000000000000000000000000000000000000000000000000000000000 !
b10000000000000000000000000000000000000000000000000000000000000000000000000000000000000000000000000000000000000000000000000000000000000000000000000 &
b10010001 #
b10010001 %
b10010001 $
#1470000
b100000000000000000000000000000000000000000000000000000000000000000000000000000000000000000000000000000000000000000000000000000000000000000000000000 !
b100000000000000000000000000000000000000000000000000000000000000000000000000000000000000000000000000000000000000000000000000000000000000000000000000 &
b10010010 #
b10010010 %
b10010010 $
#1480000
b1000000000000000000000000000000000000000000000000000000000000000000000000000000000000000000000000000000000000000000000000000000000000000000000000000 !
b1000000000000000000000000000000000000000000000000000000000000000000000000000000000000000000000000000000000000000000000000000000000000000000000000000 &
b10010011 #
b10010011 %
b10010011 $
#1490000
b10000000000000000000000000000000000000000000000000000000000000000000000000000000000000000000000000000000000000000000000000000000000000000000000000000 !
b10000000000000000000000000000000000000000000000000000000000000000000000000000000000000000000000000000000000000000000000000000000000000000000000000000 &
b10010100 #
b10010100 %
b10010100 $
#1500000
b100000000000000000000000000000000000000000000000000000000000000000000000000000000000000000000000000000000000000000000000000000000000000000000000000000 !
b100000000000000000000000000000000000000000000000000000000000000000000000000000000000000000000000000000000000000000000000000000000000000000000000000000 &
b10010101 #
b10010101 %
b10010101 $
#1510000
b1000000000000000000000000000000000000000000000000000000000000000000000000000000000000000000000000000000000000000000000000000000000000000000000000000000 !
b1000000000000000000000000000000000000000000000000000000000000000000000000000000000000000000000000000000000000000000000000000000000000000000000000000000 &
b10010110 #
b10010110 %
b10010110 $
#1520000
b10000000000000000000000000000000000000000000000000000000000000000000000000000000000000000000000000000000000000000000000000000000000000000000000000000000 !
b10000000000000000000000000000000000000000000000000000000000000000000000000000000000000000000000000000000000000000000000000000000000000000000000000000000 &
b10010111 #
b10010111 %
b10010111 $
#1530000
b100000000000000000000000000000000000000000000000000000000000000000000000000000000000000000000000000000000000000000000000000000000000000000000000000000000 !
b100000000000000000000000000000000000000000000000000000000000000000000000000000000000000000000000000000000000000000000000000000000000000000000000000000000 &
b10011000 #
b10011000 %
b10011000 $
#1540000
b1000000000000000000000000000000000000000000000000000000000000000000000000000000000000000000000000000000000000000000000000000000000000000000000000000000000 !
b1000000000000000000000000000000000000000000000000000000000000000000000000000000000000000000000000000000000000000000000000000000000000000000000000000000000 &
b10011001 #
b10011001 %
b10011001 $
#1550000
b10000000000000000000000000000000000000000000000000000000000000000000000000000000000000000000000000000000000000000000000000000000000000000000000000000000000 !
b10000000000000000000000000000000000000000000000000000000000000000000000000000000000000000000000000000000000000000000000000000000000000000000000000000000000 &
b10011010 #
b10011010 %
b10011010 $
#1560000
b100000000000000000000000000000000000000000000000000000000000000000000000000000000000000000000000000000000000000000000000000000000000000000000000000000000000 !
b100000000000000000000000000000000000000000000000000000000000000000000000000000000000000000000000000000000000000000000000000000000000000000000000000000000000 &
b10011011 #
b10011011 %
b10011011 $
#1570000
b1000000000000000000000000000000000000000000000000000000000000000000000000000000000000000000000000000000000000000000000000000000000000000000000000000000000000 !
b1000000000000000000000000000000000000000000000000000000000000000000000000000000000000000000000000000000000000000000000000000000000000000000000000000000000000 &
b10011100 #
b10011100 %
b10011100 $
#1580000
b10000000000000000000000000000000000000000000000000000000000000000000000000000000000000000000000000000000000000000000000000000000000000000000000000000000000000 !
b10000000000000000000000000000000000000000000000000000000000000000000000000000000000000000000000000000000000000000000000000000000000000000000000000000000000000 &
b10011101 #
b10011101 %
b10011101 $
#1590000
b100000000000000000000000000000000000000000000000000000000000000000000000000000000000000000000000000000000000000000000000000000000000000000000000000000000000000 !
b100000000000000000000000000000000000000000000000000000000000000000000000000000000000000000000000000000000000000000000000000000000000000000000000000000000000000 &
b10011110 #
b10011110 %
b10011110 $
#1600000
b1000000000000000000000000000000000000000000000000000000000000000000000000000000000000000000000000000000000000000000000000000000000000000000000000000000000000000 !
b1000000000000000000000000000000000000000000000000000000000000000000000000000000000000000000000000000000000000000000000000000000000000000000000000000000000000000 &
b10011111 #
b10011111 %
b10011111 $
#1610000
b10000000000000000000000000000000000000000000000000000000000000000000000000000000000000000000000000000000000000000000000000000000000000000000000000000000000000000 !
b10000000000000000000000000000000000000000000000000000000000000000000000000000000000000000000000000000000000000000000000000000000000000000000000000000000000000000 &
b10100000 #
b10100000 %
b10100000 $
